{
  "key": "ContentAreaBlock",
  "displayName": "Content Area Block",
  "description": "",
  "baseType": "component",
  "sortOrder": 0,
  "mayContainTypes": [],
  "mediaFileExtensions": [],
  "compositionBehaviors": [],
  "properties": {
    "ContentAreaBlockProperty": {
      "type": "array",
      "displayName": "Content Area lock Property",
      "description": "",
      "localized": false,
      "required": false,
      "group": "Information",
      "sortOrder": 0,
      "editorSettings": {},
      "items": {
        "type": "content",
        "allowedTypes": [],
        "restrictedTypes": []
      }
    }
  }
}